al78tools/__init__.py
al78tools/cli/__init__.py
al78tools/cli/cli_colors.py
al78tools/pysetup/__init__.py
al78tools/pysetup/first_run.py
al78tools/pysetup/tools.py
al78tools-1.0.2.dist-info/METADATA
al78tools-1.0.2.dist-info/WHEEL
al78tools-1.0.2.dist-info/top_level.txt
al78tools-1.0.2.dist-info/RECORD
