Metadata-Version: 2.1
Name: al78tools
Version: 1.0.2
Summary: Tools for PySetup etc.
Home-page: https://gitlab.com/alda78/al78tools
Author: Ales Adamek
Author-email: alda78@seznam.cz
License: MIT
Classifier: Programming Language :: Python :: 3
Classifier: License :: OSI Approved :: MIT License
Classifier: Operating System :: OS Independent
Requires-Python: >=3.6
Requires-Dist: platformdirs
